fdfs_client/__init__.py
fdfs_client/client.py
fdfs_client/connection.py
fdfs_client/exceptions.py
fdfs_client/fdfs_protol.py
fdfs_client/fdfs_test.py
fdfs_client/storage_client.py
fdfs_client/tracker_client.py
fdfs_client/utils.py
fdfs_client_py3-1.0.0.dist-info/LICENSE
fdfs_client_py3-1.0.0.dist-info/METADATA
fdfs_client_py3-1.0.0.dist-info/WHEEL
fdfs_client_py3-1.0.0.dist-info/top_level.txt
fdfs_client_py3-1.0.0.dist-info/RECORD
