Metadata-Version: 2.1
Name: fdfs-client-py3
Version: 1.0.0
Summary: python3 fastdfs package
Home-page: https://github.com/smartlz/fdfs-client-py3
Author: smartli
Author-email: smartli_it@163.com
License: UNKNOWN
Platform: UNKNOWN
Classifier: Programming Language :: Python :: 3
Classifier: License :: OSI Approved :: MIT License
Classifier: Operating System :: OS Independent
Requires-Python: >=3.5
